openicl_nolabel/__init__.py
openicl_nolabel/icl_dataset_reader.py
openicl_nolabel/icl_prompt_template.py
openicl_nolabel/icl_evaluator/__init__.py
openicl_nolabel/icl_evaluator/icl_acc_evaluator.py
openicl_nolabel/icl_evaluator/icl_api_evaluator.py
openicl_nolabel/icl_evaluator/icl_base_evaluator.py
openicl_nolabel/icl_evaluator/icl_bleu_evaluator.py
openicl_nolabel/icl_evaluator/icl_rouge_evaluator.py
openicl_nolabel/icl_evaluator/icl_squad_evaluator.py
openicl_nolabel/icl_inferencer/__init__.py
openicl_nolabel/icl_inferencer/icl_base_inferencer.py
openicl_nolabel/icl_inferencer/icl_channel_inferencer.py
openicl_nolabel/icl_inferencer/icl_cot_inferencer.py
openicl_nolabel/icl_inferencer/icl_gen_inferencer.py
openicl_nolabel/icl_inferencer/icl_ppl_inferencer.py
openicl_nolabel/icl_retriever/__init__.py
openicl_nolabel/icl_retriever/icl_base_retriever.py
openicl_nolabel/icl_retriever/icl_bm25_retriever.py
openicl_nolabel/icl_retriever/icl_dpp_retriever.py
openicl_nolabel/icl_retriever/icl_mdl_retriever.py
openicl_nolabel/icl_retriever/icl_random_retriever.py
openicl_nolabel/icl_retriever/icl_topk_retriever.py
openicl_nolabel/icl_retriever/icl_votek_retriever.py
openicl_nolabel/icl_retriever/icl_zero_retriever.py
openicl_nolabel/utils/__init__.py
openicl_nolabel/utils/api_service.py
openicl_nolabel/utils/calculate.py
openicl_nolabel/utils/check_type.py
openicl_nolabel/utils/collators.py
openicl_nolabel/utils/icl_common_utils.py
openicl_nolabel/utils/logging.py
openicl_nolabel-0.0.2.dist-info/METADATA
openicl_nolabel-0.0.2.dist-info/WHEEL
openicl_nolabel-0.0.2.dist-info/top_level.txt
openicl_nolabel-0.0.2.dist-info/RECORD
